runtime/__init__.py
runtime/config.py
runtime/http_client.py
runtime/main.py
runtime_mcp-0.1.2.dist-info/METADATA
runtime_mcp-0.1.2.dist-info/WHEEL
runtime_mcp-0.1.2.dist-info/entry_points.txt
runtime_mcp-0.1.2.dist-info/licenses/LICENSE
runtime_mcp-0.1.2.dist-info/RECORD
