Metadata-Version: 2.4
Name: runtime-mcp
Version: 0.1.2
Summary: MCP Runtime client for accessing cloud-based MCP capabilities
Project-URL: Homepage, https://github.com/lincloud-io/RunTime
Project-URL: Repository, https://github.com/lincloud-io/RunTime.git
Author: Runtime MCP
License: MIT
License-File: LICENSE
Keywords: ai,knowledge-base,mcp,runtime,task-management
Requires-Python: >=3.9
